disjunctive_nn/__init__.py
disjunctive_nn/dnn_.py
disjunctive_nn-0.1.5.dist-info/LICENCE.txt
disjunctive_nn-0.1.5.dist-info/METADATA
disjunctive_nn-0.1.5.dist-info/WHEEL
disjunctive_nn-0.1.5.dist-info/top_level.txt
disjunctive_nn-0.1.5.dist-info/RECORD
