Metadata-Version: 2.1
Name: disjunctive-nn
Version: 0.1.5
Summary: PyTorch implementation of Disjunctive Normal Networks
Home-page: https://github.com/tsitsimis/disjunctive-normal-networks
Author: Theodore Tsitsimis
Author-email: th.tsitsimis@gmail.com
License: BSD
Platform: UNKNOWN
Classifier: License :: OSI Approved
Classifier: Programming Language :: Python :: 3
Classifier: Programming Language :: Python :: 3.7
Requires-Dist: numpy (>=1.19.1)
Requires-Dist: matplotlib (>=3.3.0)
Requires-Dist: scikit-learn (>=0.23.2)
Requires-Dist: torch (>=1.6.0+cpu)
